gdpy/__init__.py
gdpy/api.py
gdpy/auth.py
gdpy/compat.py
gdpy/defaults.py
gdpy/exceptions.py
gdpy/http.py
gdpy/models.py
gdpy/utils.py
gdpy/version.py
gdpy/yml_utils.py
gdpy-0.1.17.dist-info/METADATA
gdpy-0.1.17.dist-info/WHEEL
gdpy-0.1.17.dist-info/pbr.json
gdpy-0.1.17.dist-info/top_level.txt
gdpy-0.1.17.dist-info/RECORD
