Metadata-Version: 2.1
Name: gdpy
Version: 0.1.17
Summary: GeneDock Official Python SDK
Home-page: https://gitlab.genedock.com/genedock/gdpy
Author: genedock
Author-email: gdpy@genedock.com
License: UNKNOWN
Platform: UNKNOWN
Classifier: Intended Audience :: Developers
Classifier: Operating System :: OS Independent
Classifier: Programming Language :: Python
Classifier: Programming Language :: Python :: 2
Classifier: Programming Language :: Python :: 2.6
Classifier: Programming Language :: Python :: 2.7
Classifier: Programming Language :: Python :: 3
Classifier: Programming Language :: Python :: 3.3
Classifier: Programming Language :: Python :: 3.4
Classifier: Programming Language :: Python :: 3.5
Requires-Dist: PyYAML
Requires-Dist: requests (>=2.21.0)
Requires-Dist: ndg-httpsclient (==0.5.1) ; (python_version<"2.7.9")
Requires-Dist: pyOpenSSL (==18.0.0) ; (python_version<"2.7.9")
Requires-Dist: pyasn1 (==0.4.4) ; (python_version<"2.7.9")
